SmartLogin/Errors.py
SmartLogin/Login.py
SmartLogin/__init__.py
SmartLogin/command.py
SmartLogin/finder.py
SmartLogin/monitor.py
SmartLogin/resource/chromedriver
smartlogin-0.0.1.dist-info/DESCRIPTION.rst
smartlogin-0.0.1.dist-info/METADATA
smartlogin-0.0.1.dist-info/RECORD
smartlogin-0.0.1.dist-info/WHEEL
smartlogin-0.0.1.dist-info/entry_points.txt
smartlogin-0.0.1.dist-info/metadata.json
smartlogin-0.0.1.dist-info/top_level.txt
